daemoniker/__init__.py
daemoniker/_daemonize_common.py
daemoniker/_daemonize_unix.py
daemoniker/_daemonize_windows.py
daemoniker/_privdrop_common.py
daemoniker/_privdrop_unix.py
daemoniker/_privdrop_windows.py
daemoniker/_signals_common.py
daemoniker/_signals_unix.py
daemoniker/_signals_windows.py
daemoniker/exceptions.py
daemoniker/utils.py
daemoniker-0.2.2.dist-info/DESCRIPTION.rst
daemoniker-0.2.2.dist-info/METADATA
daemoniker-0.2.2.dist-info/RECORD
daemoniker-0.2.2.dist-info/WHEEL
daemoniker-0.2.2.dist-info/metadata.json
daemoniker-0.2.2.dist-info/top_level.txt
